card_creator_utils/__init__.py
card_creator_utils/card_creator.py
card_creator_utils/prepare_print.py
card_creator_utils/utils.py
card_creator_utils-0.4.1.dist-info/LICENSE
card_creator_utils-0.4.1.dist-info/METADATA
card_creator_utils-0.4.1.dist-info/WHEEL
card_creator_utils-0.4.1.dist-info/top_level.txt
card_creator_utils-0.4.1.dist-info/RECORD
