Metadata-Version: 2.1
Name: card-creator-utils
Version: 0.4.1
Summary: A utility package for creating cards (including for board games) with images and text
Home-page: https://github.com/simonghrt/card-creator-utils
Author: Simon Gheeraert
Author-email: simon.gheeraert.sg@gmail.com
Classifier: Programming Language :: Python :: 3
Classifier: License :: OSI Approved :: MIT License
Classifier: Operating System :: OS Independent
Requires-Python: >=3.6
License-File: LICENSE
Requires-Dist: Pillow>=10.3.0
Requires-Dist: reportlab>=4.2.0
